LICENSE
LICENSE.txt
README.md
setup.py
auroranoaa/__init__.py
auroranoaa.egg-info/PKG-INFO
auroranoaa.egg-info/SOURCES.txt
auroranoaa.egg-info/dependency_links.txt
auroranoaa.egg-info/top_level.txt