Metadata-Version: 2.1
Name: auroranoaa
Version: 0.0.3
Summary: NOAA Aurora Wrapper for Home Assistant Integration.
Home-page: https://github.com/djtimca/aurora-api
Author: Tim Empringham
Author-email: tim.empringham@live.ca
License: apache-2.0
Download-URL: https://github.com/djtimca/aurora-api/archive/v_0.0.3.tar.gz
Keywords: NOAA,Aurora
Platform: UNKNOWN
Classifier: Development Status :: 3 - Alpha
Classifier: Intended Audience :: Developers
Classifier: Topic :: Software Development :: Build Tools
Classifier: License :: OSI Approved :: Apache Software License
Classifier: Programming Language :: Python :: 3
Classifier: Programming Language :: Python :: 3.4
Classifier: Programming Language :: Python :: 3.5
Classifier: Programming Language :: Python :: 3.6
Requires-Python: >=3.6
License-File: LICENSE
License-File: LICENSE.txt
